{
    "Ar36": {
        "error": 0.00034350443923120074,
        "error_type": "SEM",
        "filter_outliers_dict": {
            "filter_outliers": true,
            "iterations": 1,
            "std_devs": 3,
            "use_iqr_filtering": false,
            "use_standard_deviation_filtering": false
        },
        "fit": "linear",
        "fn": 118,
        "include_baseline_error": true,
        "n": 120,
        "outlier_excluded": [
            0,
            1
        ],
        "reviewed": true,
        "user_excluded": [],
        "value": 0.013297997014477833
    },
    "Ar37": {
        "error": 0.006206139208790539,
        "error_type": "SEM",
        "filter_outliers_dict": {
            "filter_outliers": true,
            "iterations": 1,
            "std_devs": 3,
            "use_iqr_filtering": false,
            "use_standard_deviation_filtering": false
        },
        "fit": "linear",
        "fn": 120,
        "include_baseline_error": true,
        "n": 120,
        "outlier_excluded": [],
        "reviewed": true,
        "user_excluded": [],
        "value": 0.09234887492142904
    },
    "Ar38": {
        "error": 0.006047070534890122,
        "error_type": "SEM",
        "filter_outliers_dict": {
            "filter_outliers": true,
            "iterations": 1,
            "std_devs": 3,
            "use_iqr_filtering": false,
            "use_standard_deviation_filtering": false
        },
        "fit": "linear",
        "fn": 120,
        "include_baseline_error": true,
        "n": 120,
        "outlier_excluded": [],
        "reviewed": true,
        "user_excluded": [],
        "value": 0.3868161411733866
    },
    "Ar39": {
        "error": 0.01756339599910599,
        "error_type": "SEM",
        "filter_outliers_dict": {
            "filter_outliers": true,
            "iterations": 1,
            "std_devs": 3,
            "use_iqr_filtering": false,
            "use_standard_deviation_filtering": false
        },
        "fit": "linear",
        "fn": 120,
        "include_baseline_error": true,
        "n": 120,
        "outlier_excluded": [],
        "reviewed": true,
        "user_excluded": [],
        "value": 25.595287059927514
    },
    "Ar40": {
        "error": 0.06506693299581873,
        "error_type": "SEM",
        "filter_outliers_dict": {
            "filter_outliers": true,
            "iterations": 1,
            "std_devs": 3,
            "use_iqr_filtering": false,
            "use_standard_deviation_filtering": false
        },
        "fit": "linear",
        "fn": 120,
        "include_baseline_error": true,
        "n": 120,
        "outlier_excluded": [],
        "reviewed": true,
        "user_excluded": [],
        "value": 966.499986182462
    },
    "Ar41": {
        "error": 0.025494961142110494,
        "error_type": "SEM",
        "filter_outliers_dict": {
            "filter_outliers": true,
            "iterations": 1,
            "std_devs": 2
        },
        "fit": "average",
        "value": -0.3058126694839597
    }
}